mlsetup/__init__.py
mlsetup/__main__.py
mlsetup/creator.py
mlsetup/templates/default.zip
mlsetup-1.0.0.dist-info/LICENSE
mlsetup-1.0.0.dist-info/METADATA
mlsetup-1.0.0.dist-info/WHEEL
mlsetup-1.0.0.dist-info/dependency_links.txt
mlsetup-1.0.0.dist-info/entry_points.txt
mlsetup-1.0.0.dist-info/top_level.txt
mlsetup-1.0.0.dist-info/RECORD
