Metadata-Version: 2.1
Name: mlsetup
Version: 1.0.0
Summary: A simple cli utility to generate ML project structure for quickly starting ML projects
Home-page: https://github.com/vikramsoni2/mlsetup
Author: Vikram Soni
Author-email: vikram9880@gmail.com
License: MIT
Platform: UNKNOWN
Classifier: License :: OSI Approved :: MIT License
Classifier: Programming Language :: Python :: 2.7
Classifier: Programming Language :: Python :: 3
Classifier: Programming Language :: Python :: 3.7
Requires-Python: >=2.7
Requires-Dist: click
Requires-Dist: importlib-resources
